phenomics/__init__.py
phenomics/core.py
phenomics-0.0.1.dist-info/licenses/LICENSE
phenomics-0.0.1.dist-info/METADATA
phenomics-0.0.1.dist-info/WHEEL
phenomics-0.0.1.dist-info/top_level.txt
phenomics-0.0.1.dist-info/RECORD
