Metadata-Version: 2.4
Name: phenomics
Version: 0.0.1
Summary: Dummy phenomics package for PyPI testing
Author: Prabahar Ravichandran
License: MIT
Requires-Python: >=3.9
License-File: LICENSE
Dynamic: license-file
